WeGroupChatBot/__init__.py
WeGroupChatBot/group_chat_bot.py
wegroupchatBot-0.0.7.dist-info/LICENSE
wegroupchatBot-0.0.7.dist-info/METADATA
wegroupchatBot-0.0.7.dist-info/WHEEL
wegroupchatBot-0.0.7.dist-info/top_level.txt
wegroupchatBot-0.0.7.dist-info/RECORD
