Metadata-Version: 2.1
Name: wegroupchatBot
Version: 0.0.7
Summary: group chat WeGroupChatBot for Wechat of enterprise 企业微信群机器人接口
Home-page: https://github.com/cosco-chiyz/wegroupchatbot
Author: shen yang
Author-email: cnshenyang@outlook.com
License: MIT
Download-URL: https://github.com/bonashen/wegroupchatBot/tarball/0.0.7
Keywords: wechat,groupchat,WeGroupChatBot
Platform: UNKNOWN
Classifier: Intended Audience :: Developers
Classifier: License :: OSI Approved :: MIT License
Classifier: Programming Language :: Python :: 3
Requires-Dist: requests (>=2.25.1)
Requires-Dist: pytest
Requires-Dist: six
